smiler_tools/__init__.py
smiler_tools/config.py
smiler_tools/experiment.py
smiler_tools/image_processing.py
smiler_tools/models.py
smiler_tools/parameters.py
smiler_tools/runner.py
smiler_tools/utils.py
smiler_tools-1.3.0.dist-info/LICENSE
smiler_tools-1.3.0.dist-info/METADATA
smiler_tools-1.3.0.dist-info/WHEEL
smiler_tools-1.3.0.dist-info/top_level.txt
smiler_tools-1.3.0.dist-info/RECORD
