Metadata-Version: 2.1
Name: smiler-tools
Version: 1.3.0
Summary: Helper package for SMILER.
Home-page: https://github.com/tsotsoslab/SMILER
Author: Toni Kunic
Author-email: tk@eecs.yorku.ca
License: UNKNOWN
Platform: UNKNOWN
Classifier: Programming Language :: Python :: 3
Classifier: License :: OSI Approved :: GNU Lesser General Public License v3 (LGPLv3)
Classifier: Operating System :: POSIX :: Linux
Requires-Dist: numpy
Requires-Dist: pillow (==5.1)
Requires-Dist: scipy (==1.2.1)
